abcclassroom/__init__.py
abcclassroom/__main__.py
abcclassroom/clone.py
abcclassroom/config.py
abcclassroom/distribute.py
abcclassroom/feedback.py
abcclassroom/github.py
abcclassroom/notebook.py
abcclassroom/ok.py
abcclassroom/quickstart.py
abcclassroom/scrub_feedback.py
abcclassroom/template.py
abcclassroom/utils.py
abcclassroom/example-data/config.yml
abcclassroom/example-data/readme.md
abcclassroom/example-data/sample_roster.csv
abcclassroom/example-data/extra_files/.gitignore
abcclassroom/example-data/extra_files/readme.md
abc_classroom-0.1.9.dist-info/LICENSE.rst
abc_classroom-0.1.9.dist-info/METADATA
abc_classroom-0.1.9.dist-info/WHEEL
abc_classroom-0.1.9.dist-info/entry_points.txt
abc_classroom-0.1.9.dist-info/top_level.txt
abc_classroom-0.1.9.dist-info/RECORD
