Metadata-Version: 2.1
Name: abc-classroom
Version: 0.1.9
Summary: Efficiently manage github classroom assignments from the command line.
Home-page: https://github.com/earthlab/abc-classroom
Maintainer: Leah Wasser
Maintainer-email: leah.wasser@colorado.edu
License: BSD
Platform: UNKNOWN
Classifier: Intended Audience :: Developers
Classifier: License :: OSI Approved :: BSD License
Classifier: Programming Language :: Python
Classifier: Topic :: Software Development
Classifier: Operating System :: Microsoft :: Windows
Classifier: Operating System :: POSIX
Classifier: Operating System :: Unix
Classifier: Operating System :: MacOS
Requires-Dist: nbclean
Requires-Dist: jinja2
Requires-Dist: papermill
Requires-Dist: nbformat
Requires-Dist: ruamel.yaml
Requires-Dist: github3.py
